inferlessalert/__init__.py
inferlessalert-0.0.1.dist-info/LICENSE.txt
inferlessalert-0.0.1.dist-info/METADATA
inferlessalert-0.0.1.dist-info/WHEEL
inferlessalert-0.0.1.dist-info/top_level.txt
inferlessalert-0.0.1.dist-info/RECORD
