Metadata-Version: 2.1
Name: inferlessalert
Version: 0.0.1
Summary: Function to capture alerts
Home-page: UNKNOWN
Author: Ajayjayendran Arulraj
Author-email: ajay@inferless.com
License: UNKNOWN
Platform: UNKNOWN
Classifier: Programming Language :: Python :: 3
Classifier: License :: OSI Approved :: MIT License
Classifier: Operating System :: OS Independent
License-File: LICENSE.txt
